hashids.py
hashids-1.3.0.dist-info/LICENSE
hashids-1.3.0.dist-info/WHEEL
hashids-1.3.0.dist-info/METADATA
hashids-1.3.0.dist-info/RECORD
