Metadata-Version: 2.1
Name: hashids
Version: 1.3.0
Summary: Implements the hashids algorithm in python. For more information, visit http://hashids.org/
Home-page: https://hashids.org/python/
License: UNKNOWN
Author: David Aurelio
Author-email: dev@david-aurelio.com
Requires-Python: ~=2.7,~=3.5
Classifier: License :: OSI Approved :: MIT License
Classifier: Programming Language :: Python :: 2
Classifier: Programming Language :: Python :: 2.7
Classifier: Programming Language :: Python :: 3
Classifier: Programming Language :: Python :: 3.5
Classifier: Programming Language :: Python :: 3.6
Classifier: Programming Language :: Python :: 3.7
Classifier: Programming Language :: Python :: 3.8
Requires-Dist: pytest >=2.1.0 ; extra == "test"
Provides-Extra: test
